lemon/__init__.py
lemon/markdown/__init__.py
lemon/markdown/codeblock.py
lemon/markdown/header.py
lemon/markdown/lex.py
lemon/markdown/links.py
lemon/markdown/markdown.py
lemon/markdown/parse.py
lemon/markdown/serialize.py
lemon/markdown/style.py
lemon/markdown/tables.py
lemon/search.py
lemon_md-0.2.0.dist-info/METADATA
lemon_md-0.2.0.dist-info/WHEEL
lemon_md-0.2.0.dist-info/RECORD
