Metadata-Version: 2.1
Name: lemon-md
Version: 0.2.0
Summary: Easily access, serialize, and synthesize markdown information!
Author: GrandMoff100
Author-email: minecraftcrusher100@gmail.com
Requires-Python: >=3.8,<4.0
Classifier: Programming Language :: Python :: 3
Classifier: Programming Language :: Python :: 3.8
Classifier: Programming Language :: Python :: 3.9
Classifier: Programming Language :: Python :: 3.10
Classifier: Programming Language :: Python :: 3.11
